enumeratime/__init__.py
enumeratime/et.py
enumeratime-0.0.5.dist-info/DESCRIPTION.rst
enumeratime-0.0.5.dist-info/METADATA
enumeratime-0.0.5.dist-info/RECORD
enumeratime-0.0.5.dist-info/WHEEL
enumeratime-0.0.5.dist-info/metadata.json
enumeratime-0.0.5.dist-info/top_level.txt
