Metadata-Version: 2.0
Name: enumeratime
Version: 0.0.5
Summary: Einfache Prozent und Zeitangabe beim Schleifendurchlauf
Home-page: https://github.com/miweru/enumeratime
Author: Michael Ruppert
Author-email: michael.ruppert@fau.de
License: GPLV3+
Platform: UNKNOWN
Classifier: Programming Language :: Python :: 3
Classifier: License :: OSI Approved :: GNU General Public License v3 or later (GPLv3+)
Classifier: Topic :: Software Development :: Libraries :: Python Modules
Requires-Python: >=3.5
